{
  "XAUTUSDC": {
    "id": "XAUTUSDC",
    "base": "tether-gold",
    "quote": "usd-coin"
  },
  "XAUTUSDT": {
    "id": "XAUTUSDT",
    "base": "tether-gold",
    "quote": "tether"
  },
  "XRPUSDC": {
    "id": "XRPUSDC",
    "base": "xrp",
    "quote": "usd-coin"
  },
  "XRPUSDT": {
    "id": "XRPUSDT",
    "base": "xrp",
    "quote": "tether"
  },
  "TONUSDC": {
    "id": "TONUSDC",
    "base": "toncoin",
    "quote": "usd-coin"
  },
  "TONUSDT": {
    "id": "TONUSDT",
    "base": "toncoin",
    "quote": "tether"
  },
  "CCUSDC": {
    "id": "CCUSDC",
    "base": "canton",
    "quote": "usd-coin"
  },
  "CCUSDT": {
    "id": "CCUSDT",
    "base": "canton",
    "quote": "tether"
  },
  "HYPEUSDC": {
    "id": "HYPEUSDC",
    "base": "hyperliquid",
    "quote": "usd-coin"
  },
  "HYPEUSDT": {
    "id": "HYPEUSDT",
    "base": "hyperliquid",
    "quote": "tether"
  },
  "XMRUSDC": {
    "id": "XMRUSDC",
    "base": "monero",
    "quote": "usd-coin"
  },
  "XMRUSDT": {
    "id": "XMRUSDT",
    "base": "monero",
    "quote": "tether"
  },
  "NEARUSDC": {
    "id": "NEARUSDC",
    "base": "near",
    "quote": "usd-coin"
  },
  "NEARUSDT": {
    "id": "NEARUSDT",
    "base": "near",
    "quote": "tether"
  },
  "EURIUSDC": {
    "id": "EURIUSDC",
    "base": "eurite",
    "quote": "usd-coin"
  },
  "EURIUSDT": {
    "id": "EURIUSDT",
    "base": "eurite",
    "quote": "tether"
  },
  "ASTERUSDT": {
    "id": "ASTERUSDT",
    "base": "aster",
    "quote": "tether"
  },
  "ASTERUSDC": {
    "id": "ASTERUSDC",
    "base": "aster",
    "quote": "usd-coin"
  },
  "CHZUSDC": {
    "id": "CHZUSDC",
    "base": "chiliz",
    "quote": "usd-coin"
  },
  "CHZUSDT": {
    "id": "CHZUSDT",
    "base": "chiliz",
    "quote": "tether"
  },
  "LINKUSDC": {
    "id": "LINKUSDC",
    "base": "chainlink",
    "quote": "usd-coin"
  },
  "LINKUSDT": {
    "id": "LINKUSDT",
    "base": "chainlink",
    "quote": "tether"
  },
  "BTCUSDC": {
    "id": "BTCUSDC",
    "base": "bitcoin",
    "quote": "usd-coin"
  },
  "BTCUSDT": {
    "id": "BTCUSDT",
    "base": "bitcoin",
    "quote": "tether"
  },
  "UNIUSDC": {
    "id": "UNIUSDC",
    "base": "uniswap",
    "quote": "usd-coin"
  },
  "UNIUSDT": {
    "id": "UNIUSDT",
    "base": "uniswap",
    "quote": "tether"
  },
  "ETHUSDC": {
    "id": "ETHUSDC",
    "base": "ethereum",
    "quote": "usd-coin"
  },
  "ETHUSDT": {
    "id": "ETHUSDT",
    "base": "ethereum",
    "quote": "tether"
  },
  "MNTUSDC": {
    "id": "MNTUSDC",
    "base": "mantle",
    "quote": "usd-coin"
  },
  "MNTUSDT": {
    "id": "MNTUSDT",
    "base": "mantle",
    "quote": "tether"
  },
  "DOTUSDC": {
    "id": "DOTUSDC",
    "base": "polkadot",
    "quote": "usd-coin"
  },
  "DOTUSDT": {
    "id": "DOTUSDT",
    "base": "polkadot",
    "quote": "tether"
  },
  "AAVEUSDC": {
    "id": "AAVEUSDC",
    "base": "aave",
    "quote": "usd-coin"
  },
  "AAVEUSDT": {
    "id": "AAVEUSDT",
    "base": "aave",
    "quote": "tether"
  },
  "PAXGUSDC": {
    "id": "PAXGUSDC",
    "base": "pax-gold",
    "quote": "usd-coin"
  },
  "PAXGUSDT": {
    "id": "PAXGUSDT",
    "base": "pax-gold",
    "quote": "tether"
  },
  "USDEUSDC": {
    "id": "USDEUSDC",
    "base": "ethena-usde",
    "quote": "usd-coin"
  },
  "USDEUSDT": {
    "id": "USDEUSDT",
    "base": "ethena-usde",
    "quote": "tether"
  },
  "TRXUSDC": {
    "id": "TRXUSDC",
    "base": "tron",
    "quote": "usd-coin"
  },
  "TRXUSDT": {
    "id": "TRXUSDT",
    "base": "tron",
    "quote": "tether"
  },
  "BGBUSDC": {
    "id": "BGBUSDC",
    "base": "bitget-token",
    "quote": "usd-coin"
  },
  "BGBUSDT": {
    "id": "BGBUSDT",
    "base": "bitget-token",
    "quote": "tether"
  },
  "XLMUSDC": {
    "id": "XLMUSDC",
    "base": "stellar",
    "quote": "usd-coin"
  },
  "XLMUSDT": {
    "id": "XLMUSDT",
    "base": "stellar",
    "quote": "tether"
  },
  "EURRUSDC": {
    "id": "EURRUSDC",
    "base": "stablr-euro",
    "quote": "usd-coin"
  },
  "EURRUSDT": {
    "id": "EURRUSDT",
    "base": "stablr-euro",
    "quote": "tether"
  },
  "LTCUSDC": {
    "id": "LTCUSDC",
    "base": "litecoin",
    "quote": "usd-coin"
  },
  "LTCUSDT": {
    "id": "LTCUSDT",
    "base": "litecoin",
    "quote": "tether"
  },
  "TAOUSDC": {
    "id": "TAOUSDC",
    "base": "bittensor",
    "quote": "usd-coin"
  },
  "TAOUSDT": {
    "id": "TAOUSDT",
    "base": "bittensor",
    "quote": "tether"
  },
  "AVAXUSDC": {
    "id": "AVAXUSDC",
    "base": "avalanche",
    "quote": "usd-coin"
  },
  "AVAXUSDT": {
    "id": "AVAXUSDT",
    "base": "avalanche",
    "quote": "tether"
  },
  "ALGOUSDT": {
    "id": "ALGOUSDT",
    "base": "algorand",
    "quote": "tether"
  },
  "ALGOUSDC": {
    "id": "ALGOUSDC",
    "base": "algorand",
    "quote": "usd-coin"
  },
  "SOLUSDC": {
    "id": "SOLUSDC",
    "base": "solana",
    "quote": "usd-coin"
  },
  "SOLUSDT": {
    "id": "SOLUSDT",
    "base": "solana",
    "quote": "tether"
  },
  "SUIUSDC": {
    "id": "SUIUSDC",
    "base": "sui",
    "quote": "usd-coin"
  },
  "SUIUSDT": {
    "id": "SUIUSDT",
    "base": "sui",
    "quote": "tether"
  },
  "DOGEUSDC": {
    "id": "DOGEUSDC",
    "base": "dogecoin",
    "quote": "usd-coin"
  },
  "DOGEUSDT": {
    "id": "DOGEUSDT",
    "base": "dogecoin",
    "quote": "tether"
  },
  "BCHUSDC": {
    "id": "BCHUSDC",
    "base": "bitcoin-cash",
    "quote": "usd-coin"
  },
  "BCHUSDT": {
    "id": "BCHUSDT",
    "base": "bitcoin-cash",
    "quote": "tether"
  },
  "BNBUSDC": {
    "id": "BNBUSDC",
    "base": "bnb",
    "quote": "usd-coin"
  },
  "BNBUSDT": {
    "id": "BNBUSDT",
    "base": "bnb",
    "quote": "tether"
  },
  "CROUSDC": {
    "id": "CROUSDC",
    "base": "cronos",
    "quote": "usd-coin"
  },
  "CROUSDT": {
    "id": "CROUSDT",
    "base": "cronos",
    "quote": "tether"
  },
  "WBTCUSDC": {
    "id": "WBTCUSDC",
    "base": "wrapped-bitcoin",
    "quote": "usd-coin"
  },
  "WBTCUSDT": {
    "id": "WBTCUSDT",
    "base": "wrapped-bitcoin",
    "quote": "tether"
  },
  "ZECUSDC": {
    "id": "ZECUSDC",
    "base": "zcash",
    "quote": "usd-coin"
  },
  "ZECUSDT": {
    "id": "ZECUSDT",
    "base": "zcash",
    "quote": "tether"
  },
  "ZKUSDC": {
    "id": "ZKUSDC",
    "base": "zksync",
    "quote": "usd-coin"
  },
  "ZKUSDT": {
    "id": "ZKUSDT",
    "base": "zksync",
    "quote": "tether"
  },
  "STETHUSDC": {
    "id": "STETHUSDC",
    "base": "lido-staked-ether",
    "quote": "usd-coin"
  },
  "STETHUSDT": {
    "id": "STETHUSDT",
    "base": "lido-staked-ether",
    "quote": "tether"
  },
  "USD1USDC": {
    "id": "USD1USDC",
    "base": "usd1",
    "quote": "usd-coin"
  },
  "USD1USDT": {
    "id": "USD1USDT",
    "base": "usd1",
    "quote": "tether"
  },
  "ADAUSDC": {
    "id": "ADAUSDC",
    "base": "cardano",
    "quote": "usd-coin"
  },
  "ADAUSDT": {
    "id": "ADAUSDT",
    "base": "cardano",
    "quote": "tether"
  },
  "ZROUSDC": {
    "id": "ZROUSDC",
    "base": "layer-zero",
    "quote": "usd-coin"
  },
  "ZROUSDT": {
    "id": "ZROUSDT",
    "base": "layer-zero",
    "quote": "tether"
  }
}
