{
  "display_name": "Binance",
  "kind": "cex",
  "about": {
    "en": "Binance is a centralized cryptocurrency exchange that offers spot, derivatives, and other trading services globally.",
    "es": "Binance es un exchange de criptomonedas centralizado que ofrece trading spot, derivados y otros servicios a nivel global.",
    "ca": "Binance \u00e9s un exchange de criptomonedes centralitzat que ofereix trading spot, derivats i altres serveis a nivell global."
  },
  "rank": 1,
  "urls": {
    "Website": "https://www.binance.com/"
  },
  "icon": "icons/platform/binance.svg"
}
